demuxnet/__init__.py
demuxnet/__main__.py
demuxnet/compare_with_other_tools.ipynb
demuxnet/demuxnet.py
demuxnet/main.ipynb
demuxnet/models.py
demuxnet/prediction.csv
demuxnet/test.ipynb
demuxnet/utils.py
demuxnet/__pycache__/models.cpython-38.pyc
demuxnet/__pycache__/utils.cpython-38.pyc
demuxnet-1.1.6.dist-info/METADATA
demuxnet-1.1.6.dist-info/WHEEL
demuxnet-1.1.6.dist-info/entry_points.txt
demuxnet-1.1.6.dist-info/top_level.txt
demuxnet-1.1.6.dist-info/RECORD
