Metadata-Version: 2.1
Name: demuxnet
Version: 1.1.6
Summary: Machine learning augmented sample demultiplexing of pooled single-cell RNA-seq data
Home-page: https://github.com/paddi1990/DemuxNet
Author: You Wu
Author-email: wuyou1990@sjtu.edu.cn
Classifier: Programming Language :: Python :: 3
Classifier: License :: OSI Approved :: MIT License
Classifier: Operating System :: OS Independent
Requires-Python: >=3.6
Requires-Dist: requests
Requires-Dist: numpy
Requires-Dist: rpy2
Requires-Dist: pandas
Requires-Dist: torch
Requires-Dist: scikit-learn
Requires-Dist: scipy
